LICENSE.txt
README.md
setup.cfg
setup.py
Topsis_Shikhar_102083055/__init__.py
Topsis_Shikhar_102083055.egg-info/PKG-INFO
Topsis_Shikhar_102083055.egg-info/SOURCES.txt
Topsis_Shikhar_102083055.egg-info/dependency_links.txt
Topsis_Shikhar_102083055.egg-info/requires.txt
Topsis_Shikhar_102083055.egg-info/top_level.txt