Metadata-Version: 2.1
Name: Topsis-Shikhar-102083055
Version: 1.0
Summary: Topsis Calculation
Home-page: https://github.com/shikharsaini
Author: Shikhar Saini
Author-email: shikharsaini25@gmail.com
License: MIT
Keywords: Topsis,TopsisPackage
Platform: UNKNOWN
Classifier: Development Status :: 3 - Alpha
Classifier: Intended Audience :: Developers
Classifier: License :: OSI Approved :: MIT License
Classifier: Programming Language :: Python :: 3
Classifier: Programming Language :: Python :: 3.4
Classifier: Programming Language :: Python :: 3.5
Classifier: Programming Language :: Python :: 3.6
License-File: LICENSE.txt
